pip_licenses_reader/__init__.py
pip_licenses_reader-0.9.0.dist-info/LICENSE
pip_licenses_reader-0.9.0.dist-info/METADATA
pip_licenses_reader-0.9.0.dist-info/WHEEL
pip_licenses_reader-0.9.0.dist-info/top_level.txt
pip_licenses_reader-0.9.0.dist-info/RECORD
