Metadata-Version: 2.1
Name: pip-licenses-reader
Version: 0.9.0
Summary: A small module to read the information written by pip-licenses.
Home-page: https://github.com/carstencodes/pip-licenses-reader
Author: Carsten Igel
Author-email: cig@bite-that-bit.de
License: BSD-3-Clause
Keywords: application,platform,environment,development
Platform: UNKNOWN
Classifier: Development Status :: 4 - Beta
Classifier: Intended Audience :: Developers
Classifier: License :: OSI Approved :: BSD License
Classifier: Operating System :: OS Independent
Classifier: Programming Language :: Python :: 3.7
Classifier: Programming Language :: Python :: 3.8
Classifier: Programming Language :: Python :: 3.9
Classifier: Topic :: System :: Installation/Setup
Classifier: Topic :: Software Development :: Build Tools
Classifier: Topic :: Software Development :: Libraries :: Python Modules
Classifier: Topic :: Utilities
Classifier: Typing :: Typed
Requires-Python: >=3.7, < 4
Requires-Dist: packaging
